scp_ema/__init__.py
scp_ema/parser/__init__.py
scp_ema/parser/scp_ema_parser.py
wellping_ema_parser-1.0.2.dist-info/LICENSE
wellping_ema_parser-1.0.2.dist-info/METADATA
wellping_ema_parser-1.0.2.dist-info/WHEEL
wellping_ema_parser-1.0.2.dist-info/top_level.txt
wellping_ema_parser-1.0.2.dist-info/RECORD
