Metadata-Version: 2.1
Name: wellping-ema-parser
Version: 1.0.2
Summary: JSON to CSV converter for Stanford Communities Project
Home-page: https://github.com/StanfordSocialNeuroscienceLab/wellping-ema-package
Author: Ian Richard Ferguson
Author-email: IRF229@nyu.edu
License: MIT
Platform: UNKNOWN
Classifier: License :: OSI Approved :: MIT License
Classifier: Programming Language :: Python :: 3
Classifier: Programming Language :: Python :: 3.7
License-File: LICENSE
Requires-Dist: numpy
Requires-Dist: pandas
Requires-Dist: tqdm
